.gitignore
MANIFEST.in
README.txt
setup.cfg
setup.py
docs/HISTORY.txt
docs/INSTALL.txt
docs/LICENSE.GPL
docs/LICENSE.txt
operun/__init__.py
operun.media.egg-info/PKG-INFO
operun.media.egg-info/SOURCES.txt
operun.media.egg-info/dependency_links.txt
operun.media.egg-info/entry_points.txt
operun.media.egg-info/namespace_packages.txt
operun.media.egg-info/not-zip-safe
operun.media.egg-info/requires.txt
operun.media.egg-info/top_level.txt
operun/media/__init__.py
operun/media/config.py
operun/media/configure.zcml
operun/media/doi18ndude
operun/media/tests.py
operun/media/validators.py
operun/media/browser/__init__.py
operun/media/browser/configure.zcml
operun/media/browser/media.css
operun/media/browser/media.png
operun/media/browser/media.pt
operun/media/browser/media.py
operun/media/browser/transparent.png
operun/media/browser/elements/README.txt
operun/media/browser/elements/flowplayer.audio.swf
operun/media/browser/elements/flowplayer.controls.swf
operun/media/browser/elements/flowplayer.min.js
operun/media/browser/elements/flowplayer.swf
operun/media/content/__init__.py
operun/media/content/configure.zcml
operun/media/content/media.py
operun/media/interfaces/__init__.py
operun/media/interfaces/media.py
operun/media/locales/operun.media.pot
operun/media/locales/de/LC_MESSAGES/operun.media.mo
operun/media/locales/de/LC_MESSAGES/operun.media.po
operun/media/profiles/default/factorytool.xml
operun/media/profiles/default/metadata.xml
operun/media/profiles/default/rolemap.xml
operun/media/profiles/default/types.xml
operun/media/profiles/default/types/Media.xml