Metadata-Version: 1.1
Name: operun.media
Version: 3.2
Summary: A product to integrate any type of media to Plone
Home-page: https://github.com/starzel/operun.media
Author: operun.de by Stefan Antonelli
Author-email: info@operun.de
License: GPL
Keywords: Plone Audio Video Media
Platform: UNKNOWN
Classifier: Framework :: Plone
Classifier: Programming Language :: Python
Classifier: Topic :: Software Development :: Libraries :: Python Modules
